{
  "project_info": {
    "project_number": "285013628013",
    "project_id": "rentndeal-05",
    "storage_bucket": "rentndeal-05.appspot.com"
  },
  "client": [
    {
      "client_info": {
        "mobilesdk_app_id": "1:285013628013:android:b6855906df61632a0edb64",
        "android_client_info": {
          "package_name": "com.example.rentndeal"
        }
      },
      "oauth_client": [
        {
          "client_id": "285013628013-2ac5075el3gu1kcetpo66tgc3a8huvem.apps.googleusercontent.com",
          "client_type": 1,
          "android_info": {
            "package_name": "com.example.rentndeal",
            "certificate_hash": "1cb69248451025e5805e5926f7f9e58e427d8c36"
          }
        },
        {
          "client_id": "285013628013-ftf10k7jh24heto9ot6m80n041nhvs8d.apps.googleusercontent.com",
          "client_type": 3
        }
      ],
      "api_key": [
        {
          "current_key": "AIzaSyBdGF-Wlxyz8CgmlVKTvOaI3cuB85PhVEc"
        }
      ],
      "services": {
        "appinvite_service": {
          "other_platform_oauth_client": [
            {
              "client_id": "285013628013-ftf10k7jh24heto9ot6m80n041nhvs8d.apps.googleusercontent.com",
              "client_type": 3
            },
            {
              "client_id": "285013628013-2drtk2ms4c5nrfdh40n5goebumfkh26v.apps.googleusercontent.com",
              "client_type": 2,
              "ios_info": {
                "bundle_id": "com.example.rentndeal"
              }
            }
          ]
        }
      }
    },
    {
      "client_info": {
        "mobilesdk_app_id": "1:285013628013:android:4fe6b8dc29f8f2050edb64",
        "android_client_info": {
          "package_name": "com.example.rentndeal_admin_panel"
        }
      },
      "oauth_client": [
        {
          "client_id": "285013628013-ftf10k7jh24heto9ot6m80n041nhvs8d.apps.googleusercontent.com",
          "client_type": 3
        }
      ],
      "api_key": [
        {
          "current_key": "AIzaSyBdGF-Wlxyz8CgmlVKTvOaI3cuB85PhVEc"
        }
      ],
      "services": {
        "appinvite_service": {
          "other_platform_oauth_client": [
            {
              "client_id": "285013628013-ftf10k7jh24heto9ot6m80n041nhvs8d.apps.googleusercontent.com",
              "client_type": 3
            },
            {
              "client_id": "285013628013-2drtk2ms4c5nrfdh40n5goebumfkh26v.apps.googleusercontent.com",
              "client_type": 2,
              "ios_info": {
                "bundle_id": "com.example.rentndeal"
              }
            }
          ]
        }
      }
    }
  ],
  "configuration_version": "1"
}